[
  {
    "type": "get",
    "url": "/user/:id",
    "title": "Request User information",
    "name": "GetUser",
    "group": "User",
    "parameter": {
      "fields": {
        "Parameter": [
          {
            "group": "Parameter",
            "type": "ObjectId",
            "optional": false,
            "field": "id",
            "description": "<p>Users unique ID.</p>"
          }
        ]
      }
    },
    "success": {
      "fields": {
        "Success 200": [
          {
            "group": "Success 200",
            "type": "String",
            "optional": false,
            "field": "firstname",
            "description": "<p>Firstname of the User.</p>"
          }
        ]
      }
    },
    "version": "0.0.0",
    "filename": "lib/route/v1/user.js",
    "groupTitle": "User"
  },
  {
    "type": "put",
    "url": "/user/:id",
    "title": "Update User information",
    "name": "UpdateUser",
    "group": "User",
    "parameter": {
      "fields": {
        "Parameter": [
          {
            "group": "Parameter",
            "type": "ObjectId",
            "optional": false,
            "field": "id",
            "description": "<p>Users unique ID.</p>"
          },
          {
            "group": "Parameter",
            "type": "String",
            "optional": false,
            "field": "User",
            "description": "<p>'s new nickname.</p>"
          }
        ]
      }
    },
    "success": {
      "fields": {
        "Success 200": [
          {
            "group": "Success 200",
            "type": "String",
            "optional": false,
            "field": "firstname",
            "description": "<p>Firstname of the User.</p>"
          }
        ]
      }
    },
    "version": "0.0.0",
    "filename": "lib/route/v1/user.js",
    "groupTitle": "User"
  }
]
